tree_inspector/__init__.py
tree_inspector/options.py
tree_inspector/template.html
tree_inspector/tree_builder.py
tree_inspector-2.1.2.dist-info/METADATA
tree_inspector-2.1.2.dist-info/WHEEL
tree_inspector-2.1.2.dist-info/top_level.txt
tree_inspector-2.1.2.dist-info/RECORD
