Metadata-Version: 2.1
Name: tree-inspector
Version: 2.1.2
Summary: Inspect a Python object with an interactive tree view
Home-page: https://github.com/slinjhu/tree-inspector
Author: Sen Lin
Author-email: slinjhu@gmail.com
License: MIT
Platform: UNKNOWN
Requires-Python: >=3.5.0
Requires-Dist: numpy
Requires-Dist: jinja2
